setup.py
c7n_guardian/__init__.py
c7n_guardian/cli.py
c7n_guardian.egg-info/PKG-INFO
c7n_guardian.egg-info/SOURCES.txt
c7n_guardian.egg-info/dependency_links.txt
c7n_guardian.egg-info/entry_points.txt
c7n_guardian.egg-info/requires.txt
c7n_guardian.egg-info/top_level.txt