Metadata-Version: 1.1
Name: c7n-guardian
Version: 0.3
Summary: Cloud Custodian - Multi Account Guard Duty Setup
Home-page: https://github.com/capitalone/cloud-custodian
Author: Kapil Thangavelu
Author-email: kapil.foss@gmail.com
License: Apache-2.0
Platform: UNKNOWN
Classifier: Topic :: System :: Systems Administration
Classifier: Topic :: System :: Distributed Computing
